thoth/common/__init__.py
thoth/common/enums.py
thoth/common/exceptions.py
thoth/common/helpers.py
thoth/common/json.py
thoth/common/logging.py
thoth/common/openshift.py
thoth/common/py.typed
thoth/common/workflows.py
thoth/common/config/__init__.py
thoth/common/config/base.py
thoth/common/config/hardware_information.py
thoth/common/config/operating_system.py
thoth/common/config/runtime_environment.py
thoth_common-0.36.6.dist-info/LICENSE
thoth_common-0.36.6.dist-info/METADATA
thoth_common-0.36.6.dist-info/WHEEL
thoth_common-0.36.6.dist-info/top_level.txt
thoth_common-0.36.6.dist-info/RECORD
