Metadata-Version: 2.1
Name: thoth-common
Version: 0.36.6
Summary: Shared code logic in the project Thoth.
Author: Fridolin Pokorny
Author-email: fridolin@redhat.com
License: GPLv3+
License-File: LICENSE
